readma/__init__.py
readma/readma.py
readma-1.0.2a0.dist-info/LICENSE.md
readma-1.0.2a0.dist-info/METADATA
readma-1.0.2a0.dist-info/WHEEL
readma-1.0.2a0.dist-info/top_level.txt
readma-1.0.2a0.dist-info/RECORD
